odoo9_addon_email_template_qweb-9.0.1.0.0.99.dev14-py2.7-nspkg.pth
odoo9_addon_email_template_qweb-9.0.1.0.0.99.dev14.dist-info/DESCRIPTION.rst
odoo9_addon_email_template_qweb-9.0.1.0.0.99.dev14.dist-info/METADATA
odoo9_addon_email_template_qweb-9.0.1.0.0.99.dev14.dist-info/RECORD
odoo9_addon_email_template_qweb-9.0.1.0.0.99.dev14.dist-info/WHEEL
odoo9_addon_email_template_qweb-9.0.1.0.0.99.dev14.dist-info/metadata.json
odoo9_addon_email_template_qweb-9.0.1.0.0.99.dev14.dist-info/namespace_packages.txt
odoo9_addon_email_template_qweb-9.0.1.0.0.99.dev14.dist-info/top_level.txt
odoo_addons/email_template_qweb/README.rst
odoo_addons/email_template_qweb/__init__.py
odoo_addons/email_template_qweb/__openerp__.py
odoo_addons/email_template_qweb/demo/ir_ui_view.xml
odoo_addons/email_template_qweb/demo/mail_template.xml
odoo_addons/email_template_qweb/i18n/de.po
odoo_addons/email_template_qweb/i18n/el_GR.po
odoo_addons/email_template_qweb/i18n/email_template_qweb.pot
odoo_addons/email_template_qweb/i18n/es.po
odoo_addons/email_template_qweb/i18n/es_MX.po
odoo_addons/email_template_qweb/i18n/hr.po
odoo_addons/email_template_qweb/i18n/zh_CN.po
odoo_addons/email_template_qweb/models/__init__.py
odoo_addons/email_template_qweb/models/mail_template.py
odoo_addons/email_template_qweb/static/description/icon.png
odoo_addons/email_template_qweb/tests/__init__.py
odoo_addons/email_template_qweb/tests/test_mail_template_qweb.py
odoo_addons/email_template_qweb/views/mail_template.xml
